simple_salesforce_analytics/__init__.py
simple_salesforce_analytics/sf_dashboard.py
simple_salesforce_analytics/sf_report.py
simple_salesforce_analytics-0.0.1.dist-info/METADATA
simple_salesforce_analytics-0.0.1.dist-info/WHEEL
simple_salesforce_analytics-0.0.1.dist-info/licenses/LICENSE
simple_salesforce_analytics-0.0.1.dist-info/RECORD
